odoo/addons/l10n_br_nfse/README.rst
odoo/addons/l10n_br_nfse/__init__.py
odoo/addons/l10n_br_nfse/__manifest__.py
odoo/addons/l10n_br_nfse/constants/nfse.py
odoo/addons/l10n_br_nfse/demo/fiscal_document_demo.xml
odoo/addons/l10n_br_nfse/demo/product_demo.xml
odoo/addons/l10n_br_nfse/i18n/l10n_br_nfse.pot
odoo/addons/l10n_br_nfse/i18n/pt_BR.po
odoo/addons/l10n_br_nfse/models/__init__.py
odoo/addons/l10n_br_nfse/models/document.py
odoo/addons/l10n_br_nfse/models/document_line.py
odoo/addons/l10n_br_nfse/models/product_template.py
odoo/addons/l10n_br_nfse/models/res_company.py
odoo/addons/l10n_br_nfse/models/res_partner.py
odoo/addons/l10n_br_nfse/readme/CONFIGURE.rst
odoo/addons/l10n_br_nfse/readme/CONTRIBUTORS.rst
odoo/addons/l10n_br_nfse/readme/DESCRIPTION.rst
odoo/addons/l10n_br_nfse/readme/INSTALL.rst
odoo/addons/l10n_br_nfse/readme/ROADMAP.rst
odoo/addons/l10n_br_nfse/readme/USAGE.rst
odoo/addons/l10n_br_nfse/report/danfse.xml
odoo/addons/l10n_br_nfse/security/ir.model.access.csv
odoo/addons/l10n_br_nfse/static/description/icon.png
odoo/addons/l10n_br_nfse/static/description/index.html
odoo/addons/l10n_br_nfse/static/src/img/itajuba.png
odoo/addons/l10n_br_nfse/tests/__init__.py
odoo/addons/l10n_br_nfse/tests/test_fiscal_document_nfse_common.py
odoo/addons/l10n_br_nfse/views/document_line_view.xml
odoo/addons/l10n_br_nfse/views/document_view.xml
odoo/addons/l10n_br_nfse/views/product_product_view.xml
odoo/addons/l10n_br_nfse/views/product_template_view.xml
odoo/addons/l10n_br_nfse/views/res_company_view.xml
odoo12_addon_l10n_br_nfse-12.0.5.7.0.dist-info/METADATA
odoo12_addon_l10n_br_nfse-12.0.5.7.0.dist-info/WHEEL
odoo12_addon_l10n_br_nfse-12.0.5.7.0.dist-info/top_level.txt
odoo12_addon_l10n_br_nfse-12.0.5.7.0.dist-info/RECORD
